VestaRestPackage/__init__.py
VestaRestPackage/__meta__.py
VestaRestPackage/app_objects.py
VestaRestPackage/celery_conf_values.py
VestaRestPackage/celery_init.py
VestaRestPackage/default_configuration.py
VestaRestPackage/generic_rest_api.py
VestaRestPackage/jwt_.py
VestaRestPackage/logging.ini
VestaRestPackage/print_example_configuration.py
VestaRestPackage/request_authorisation.py
VestaRestPackage/reverse_proxied.py
VestaRestPackage/run_process.py
VestaRestPackage/singleton.py
VestaRestPackage/utility_rest.py
VestaRestPackage/vesta_exceptions.py
VestaRestPackage/db_struct/requests_schema.sql
VestaRestPackage/db_struct/service_invocations_schema.sql
VestaRestPackage/static/style.css
VestaRestPackage/templates/default.html
VestaRestPackage/templates/error.html
VestaRestPackage/templates/layout.html
VestaRestPackage/templates/self_test.html
VestaRestPackage/templates/tryme.html
VestaRestPackage-1.9.3.dist-info/AUTHORS.rst
VestaRestPackage-1.9.3.dist-info/LICENSE.rst
VestaRestPackage-1.9.3.dist-info/METADATA
VestaRestPackage-1.9.3.dist-info/WHEEL
VestaRestPackage-1.9.3.dist-info/entry_points.txt
VestaRestPackage-1.9.3.dist-info/top_level.txt
VestaRestPackage-1.9.3.dist-info/RECORD
