Metadata-Version: 2.1
Name: VestaRestPackage
Version: 1.9.3
Summary: Code to facilitate creation of Vesta Service Gateway.
Home-page: https://github.com/crim-ca/RESTPackage
Author: CRIM
Author-email: vestapl@crim.ca
License: Apache 2.0
Keywords: Vesta,Service,ServiceGateway
Platform: linux_x86_64
Classifier: Development Status :: 4 - Beta
Classifier: Intended Audience :: Developers
Classifier: Topic :: Software Development :: Libraries :: Application Frameworks
Classifier: License :: OSI Approved :: Apache Software License
Classifier: Natural Language :: English
Classifier: Programming Language :: Python :: 2
Classifier: Programming Language :: Python :: 2.7
Requires-Dist: Flask (==0.12.4)
Requires-Dist: pyrabbit (==1.0.1)
Requires-Dist: PyJWT (==0.4.3)
Requires-Dist: dicttoxml (==1.6.6)
Requires-Dist: VestaService (==0.4.1)
Requires-Dist: configparser
Requires-Dist: future
Requires-Dist: pymongo (==3.7.2)
Requires-Dist: Flask-PyMongo (==2.2.0)
Requires-Dist: sentry-sdk[flask]
